torch_data_bigquery/__about__.py
torch_data_bigquery/__init__.py
torch_data_bigquery/dataset/__init__.py
torch_data_bigquery/dataset/query.py
torch_data_bigquery/dataset/storage.py
torch_data_bigquery-0.0.2.dist-info/METADATA
torch_data_bigquery-0.0.2.dist-info/WHEEL
torch_data_bigquery-0.0.2.dist-info/licenses/LICENSE.txt
torch_data_bigquery-0.0.2.dist-info/RECORD
