Metadata-Version: 2.1
Name: torch-data-bigquery
Version: 0.0.2
Project-URL: Documentation, https://github.com/xando/torch-data-bigquery#readme
Project-URL: Issues, https://github.com/xando/torch-data-bigquery/issues
Project-URL: Source, https://github.com/xando/torch-data-bigquery
Author: Sebastian Pawluś
License-Expression: MIT
License-File: LICENSE.txt
Keywords: bigquery,google-cloud,pytorch,torch
Classifier: Development Status :: 4 - Beta
Classifier: Programming Language :: Python
Classifier: Programming Language :: Python :: 3.8
Classifier: Programming Language :: Python :: 3.9
Classifier: Programming Language :: Python :: 3.10
Classifier: Programming Language :: Python :: 3.11
Classifier: Programming Language :: Python :: 3.12
Classifier: Programming Language :: Python :: Implementation :: CPython
Classifier: Programming Language :: Python :: Implementation :: PyPy
Requires-Python: >=3.8
Requires-Dist: google-cloud-bigquery
Requires-Dist: google-cloud-bigquery-storage
Requires-Dist: pyarrow
Requires-Dist: torch
